<texas name="texas">
 <ilce value="8975" data-url="/tr-TR/8975/austin-icin-namaz-vakti">AUSTIN</ilce>
                                        <ilce value="8976" data-url="/tr-TR/8976/bay-city-icin-namaz-vakti">BAY CITY</ilce>
                                        <ilce value="8977" data-url="/tr-TR/8977/baytown-icin-namaz-vakti">BAYTOWN</ilce>
                                        <ilce value="8978" data-url="/tr-TR/8978/beaumont-icin-namaz-vakti">BEAUMONT</ilce>
                                        <ilce value="8979" data-url="/tr-TR/8979/college-station-icin-namaz-vakti">COLLEGE STATION</ilce>
                                        <ilce value="8980" data-url="/tr-TR/8980/conroe-icin-namaz-vakti">CONROE</ilce>
                                        <ilce value="8981" data-url="/tr-TR/8981/dallas-icin-namaz-vakti">DALLAS</ilce>
                                        <ilce value="8982" data-url="/tr-TR/8982/denton-icin-namaz-vakti">DENTON</ilce>
                                        <ilce value="8983" data-url="/tr-TR/8983/el-paso-icin-namaz-vakti">EL PASO</ilce>
                                        <ilce value="8984" data-url="/tr-TR/8984/fort-worth-icin-namaz-vakti">FORT WORTH</ilce>
                                        <ilce value="8985" data-url="/tr-TR/8985/galveston-icin-namaz-vakti">GALVESTON</ilce>
                                        <ilce value="8986" data-url="/tr-TR/8986/houston-icin-namaz-vakti">HOUSTON</ilce>
                                        <ilce value="8987" data-url="/tr-TR/8987/laredo-icin-namaz-vakti">LAREDO</ilce>
                                        <ilce value="8988" data-url="/tr-TR/8988/lubbock-icin-namaz-vakti">LUBBOCK</ilce>
                                        <ilce value="8989" data-url="/tr-TR/8989/pasadena-icin-namaz-vakti">PASADENA</ilce>
                                        <ilce value="8990" data-url="/tr-TR/8990/rosenberg-icin-namaz-vakti">ROSENBERG</ilce>
                                        <ilce value="8991" data-url="/tr-TR/8991/san-antonio-icin-namaz-vakti">SAN ANTONIO</ilce>
                                        <ilce value="8992" data-url="/tr-TR/8992/texas-city-icin-namaz-vakti">TEXAS CITY</ilce>
                                        <ilce value="8993" data-url="/tr-TR/8993/wichita-falls-icin-namaz-vakti">WICHITA FALLS</ilce>
 </texas>


  
